{"cameraMode":{"drawMode":0,"name":"Shaded","section":"Shading Mode"},"sceneLighting":true,"audioPlay":false,"sceneViewState":{"m_AlwaysRefresh":false,"showFog":true,"showSkybox":true,"showFlares":true,"showImageEffects":true,"showParticleSystems":true,"showVisualEffectGraphs":true,"m_FxEnabled":true},"in2DMode":false,"pivot":{"x":11.038619041442871,"y":-10.159303665161133,"z":-38.589881896972659},"rotation":{"x":-0.02044125646352768,"y":-0.9794532656669617,"z":0.15013378858566285,"w":-0.1333240270614624},"size":23.034183502197267,"orthographic":false}